scallopy-0.1.0.dist-info/METADATA
scallopy-0.1.0.dist-info/WHEEL
scallopy/io.py
scallopy/__init__.py
scallopy/types.py
scallopy/context.py
scallopy/collection.py
scallopy/py.typed
scallopy/torch_importer.py
scallopy/provenance.py
scallopy/scallopy.pyi
scallopy/scallopy.cpython-39-darwin.so
scallopy-0.1.0.dist-info/RECORD
