Metadata-Version: 2.1
Name: scallopy
Version: 0.1.0
